LICENSE
MANIFEST.in
README.md
setup.cfg
setup.py
minpages/__init__.py
minpages/min.py
minpages/page.py
minpages.egg-info/PKG-INFO
minpages.egg-info/SOURCES.txt
minpages.egg-info/dependency_links.txt
minpages.egg-info/entry_points.txt
minpages.egg-info/requires.txt
minpages.egg-info/top_level.txt
minpages/pages/chmod
minpages/pages/chown
minpages/pages/find
minpages/pages/grep
minpages/pages/min