Metadata-Version: 1.0
Name: minpages
Version: 0.0.12
Summary: An abbreviated man-pages
Home-page: http://github.com/brian-bk/minpages/
Author: Brian Kleszyk
Author-email: bkleszyk@gmail.com
License: GPL
Platform: UNKNOWN
